easymyweb/__init__.py
easymyweb/app.py
easymyweb/runner.py
EasyMyWeb-0.3.dist-info/METADATA
EasyMyWeb-0.3.dist-info/WHEEL
EasyMyWeb-0.3.dist-info/top_level.txt
EasyMyWeb-0.3.dist-info/RECORD
